iMVP_utils/__init__.py
iMVP_utils/clustering.py
iMVP_utils/embedding.py
iMVP_utils/interactive.py
iMVP_utils/interactive_functions.py
iMVP_utils/plots.py
iMVP_utils/utils.py
iMVP_utils/assets/style.css
iMVP_utils-0.2.5.data/scripts/iMVP_viewer.py
iMVP_utils-0.2.5.dist-info/LICENSE
iMVP_utils-0.2.5.dist-info/METADATA
iMVP_utils-0.2.5.dist-info/WHEEL
iMVP_utils-0.2.5.dist-info/top_level.txt
iMVP_utils-0.2.5.dist-info/RECORD
